{"dashboard": {"value": {"hits": 0, "uiStateJSON": "{\"P-2\":{\"vis\":{\"params\":{\"sort\":{\"columnIndex\":null,\"direction\":null}}}},\"P-3\":{\"vis\":{\"params\":{\"sort\":{\"columnIndex\":0,\"direction\":\"asc\"}}}},\"P-4\":{\"vis\":{\"legendOpen\":true}},\"P-5\":{\"vis\":{\"params\":{\"sort\":{\"columnIndex\":null,\"direction\":null}}}}}", "description": "", "timeRestore": false, "kibanaSavedObjectMeta": {"searchSourceJSON": "{\"filter\":[{\"query\":{\"query_string\":{\"analyze_wildcard\":true,\"query\":\"*\"}}}]}"}, "title": "SortingHat", "panelsJSON": "[{\"col\":1,\"columns\":[\"username\",\"name\",\"email\",\"enrollments\",\"id\",\"uuid\"],\"id\":\"SortingHat\",\"panelIndex\":1,\"row\":1,\"size_x\":7,\"size_y\":8,\"sort\":[\"metadata__updated_on\",\"desc\"],\"type\":\"search\"},{\"col\":8,\"id\":\"SortingHatUuids\",\"panelIndex\":2,\"row\":1,\"size_x\":5,\"size_y\":3,\"type\":\"visualization\"},{\"col\":8,\"id\":\"SortingHatEnrollments\",\"panelIndex\":3,\"row\":6,\"size_x\":2,\"size_y\":3,\"type\":\"visualization\"},{\"col\":10,\"id\":\"SortingHatSources\",\"panelIndex\":4,\"row\":4,\"size_x\":3,\"size_y\":3,\"type\":\"visualization\"},{\"id\":\"SortingHatProfile\",\"type\":\"visualization\",\"panelIndex\":5,\"size_x\":2,\"size_y\":2,\"col\":8,\"row\":4}]", "version": 1, "optionsJSON": "{\"darkTheme\":false}"}, "id": "SortingHat"}, "visualizations": [{"value": {"visState": "{\"title\":\"SortingHatUuids\",\"type\":\"table\",\"params\":{\"perPage\":10,\"showPartialRows\":false,\"showMeticsAtAllLevels\":false,\"sort\":{\"columnIndex\":null,\"direction\":null},\"showTotal\":true,\"totalFunc\":\"sum\"},\"aggs\":[{\"id\":\"1\",\"enabled\":true,\"type\":\"count\",\"schema\":\"metric\",\"params\":{}},{\"id\":\"2\",\"enabled\":true,\"type\":\"terms\",\"schema\":\"bucket\",\"params\":{\"field\":\"uuid\",\"size\":500,\"order\":\"desc\",\"orderBy\":\"1\"}},{\"id\":\"3\",\"enabled\":true,\"type\":\"terms\",\"schema\":\"bucket\",\"params\":{\"field\":\"username\",\"size\":5,\"order\":\"desc\",\"orderBy\":\"1\"}}],\"listeners\":{}}", "uiStateJSON": "{\"vis\":{\"params\":{\"sort\":{\"columnIndex\":null,\"direction\":null}}}}", "description": "", "kibanaSavedObjectMeta": {"searchSourceJSON": "{\"index\":\"sortinghat_events\",\"query\":{\"query_string\":{\"query\":\"*\",\"analyze_wildcard\":true}},\"filter\":[]}"}, "title": "SortingHatUuids", "version": 1}, "id": "SortingHatUuids"}, {"value": {"visState": "{\"title\":\"SortingHatEnrollments\",\"type\":\"table\",\"params\":{\"perPage\":10,\"showPartialRows\":false,\"showMeticsAtAllLevels\":false,\"sort\":{\"columnIndex\":null,\"direction\":null},\"showTotal\":false,\"totalFunc\":\"sum\"},\"aggs\":[{\"id\":\"1\",\"enabled\":true,\"type\":\"count\",\"schema\":\"metric\",\"params\":{}},{\"id\":\"2\",\"enabled\":true,\"type\":\"terms\",\"schema\":\"bucket\",\"params\":{\"field\":\"enrollments\",\"size\":30,\"order\":\"desc\",\"orderBy\":\"1\"}}],\"listeners\":{}}", "uiStateJSON": "{\"vis\":{\"params\":{\"sort\":{\"columnIndex\":null,\"direction\":null}}}}", "description": "", "kibanaSavedObjectMeta": {"searchSourceJSON": "{\"index\":\"sortinghat_events\",\"query\":{\"query_string\":{\"query\":\"*\",\"analyze_wildcard\":true}},\"filter\":[]}"}, "title": "SortingHatEnrollments", "version": 1}, "id": "SortingHatEnrollments"}, {"value": {"visState": "{\"title\":\"SortingHatSources\",\"type\":\"pie\",\"params\":{\"shareYAxis\":true,\"addTooltip\":true,\"addLegend\":true,\"legendPosition\":\"right\",\"isDonut\":false},\"aggs\":[{\"id\":\"1\",\"enabled\":true,\"type\":\"count\",\"schema\":\"metric\",\"params\":{}},{\"id\":\"2\",\"enabled\":true,\"type\":\"terms\",\"schema\":\"segment\",\"params\":{\"field\":\"source\",\"size\":5,\"order\":\"desc\",\"orderBy\":\"1\"}}],\"listeners\":{}}", "uiStateJSON": "{}", "description": "", "kibanaSavedObjectMeta": {"searchSourceJSON": "{\"index\":\"sortinghat_events\",\"query\":{\"query_string\":{\"query\":\"*\",\"analyze_wildcard\":true}},\"filter\":[]}"}, "title": "SortingHatSources", "version": 1}, "id": "SortingHatSources"}, {"value": {"visState": "{\"title\":\"SortingHatProfile\",\"type\":\"table\",\"params\":{\"perPage\":10,\"showPartialRows\":false,\"showMeticsAtAllLevels\":false,\"sort\":{\"columnIndex\":null,\"direction\":null},\"showTotal\":false,\"totalFunc\":\"sum\"},\"aggs\":[{\"id\":\"1\",\"enabled\":true,\"type\":\"count\",\"schema\":\"metric\",\"params\":{}},{\"id\":\"2\",\"enabled\":true,\"type\":\"terms\",\"schema\":\"bucket\",\"params\":{\"field\":\"profile_name\",\"size\":10,\"order\":\"desc\",\"orderBy\":\"1\"}}],\"listeners\":{}}", "uiStateJSON": "{\"vis\":{\"params\":{\"sort\":{\"columnIndex\":null,\"direction\":null}}}}", "description": "", "kibanaSavedObjectMeta": {"searchSourceJSON": "{\"index\":\"sortinghat_events\",\"query\":{\"query_string\":{\"query\":\"*\",\"analyze_wildcard\":true}},\"filter\":[]}"}, "title": "SortingHatProfile", "version": 1}, "id": "SortingHatProfile"}], "index_patterns": [{"value": {"title": "sortinghat_events", "timeFieldName": "metadata__updated_on", "fields": "[{\"name\":\"origin\",\"type\":\"string\",\"count\":0,\"scripted\":false,\"indexed\":true,\"analyzed\":false,\"doc_values\":true,\"searchable\":true,\"aggregatable\":true},{\"name\":\"source\",\"type\":\"string\",\"count\":1,\"scripted\":false,\"indexed\":true,\"analyzed\":false,\"doc_values\":true,\"searchable\":true,\"aggregatable\":true},{\"name\":\"uuid\",\"type\":\"string\",\"count\":0,\"scripted\":false,\"indexed\":true,\"analyzed\":false,\"doc_values\":true,\"searchable\":true,\"aggregatable\":true},{\"name\":\"enrollments\",\"type\":\"string\",\"count\":0,\"scripted\":false,\"indexed\":true,\"analyzed\":false,\"doc_values\":true,\"searchable\":true,\"aggregatable\":true},{\"name\":\"profile_name\",\"type\":\"string\",\"count\":0,\"scripted\":false,\"indexed\":true,\"analyzed\":false,\"doc_values\":true,\"searchable\":true,\"aggregatable\":true},{\"name\":\"name\",\"type\":\"string\",\"count\":0,\"scripted\":false,\"indexed\":true,\"analyzed\":false,\"doc_values\":true,\"searchable\":true,\"aggregatable\":true},{\"name\":\"profile_email\",\"type\":\"string\",\"count\":0,\"scripted\":false,\"indexed\":true,\"analyzed\":false,\"doc_values\":true,\"searchable\":true,\"aggregatable\":true},{\"name\":\"_source\",\"type\":\"_source\",\"count\":0,\"scripted\":false,\"indexed\":false,\"analyzed\":false,\"doc_values\":false,\"searchable\":false,\"aggregatable\":false},{\"name\":\"metadata__updated_on\",\"type\":\"date\",\"count\":0,\"scripted\":false,\"indexed\":true,\"analyzed\":false,\"doc_values\":true,\"searchable\":true,\"aggregatable\":true},{\"name\":\"id\",\"type\":\"string\",\"count\":0,\"scripted\":false,\"indexed\":true,\"analyzed\":false,\"doc_values\":true,\"searchable\":true,\"aggregatable\":true},{\"name\":\"email\",\"type\":\"string\",\"count\":0,\"scripted\":false,\"indexed\":true,\"analyzed\":false,\"doc_values\":true,\"searchable\":true,\"aggregatable\":true},{\"name\":\"username\",\"type\":\"string\",\"count\":0,\"scripted\":false,\"indexed\":true,\"analyzed\":false,\"doc_values\":true,\"searchable\":true,\"aggregatable\":true},{\"name\":\"_id\",\"type\":\"string\",\"count\":0,\"scripted\":false,\"indexed\":false,\"analyzed\":false,\"doc_values\":false,\"searchable\":false,\"aggregatable\":false},{\"name\":\"_type\",\"type\":\"string\",\"count\":0,\"scripted\":false,\"indexed\":false,\"analyzed\":false,\"doc_values\":false,\"searchable\":true,\"aggregatable\":true},{\"name\":\"_index\",\"type\":\"string\",\"count\":0,\"scripted\":false,\"indexed\":false,\"analyzed\":false,\"doc_values\":false,\"searchable\":false,\"aggregatable\":false},{\"name\":\"_score\",\"type\":\"number\",\"count\":0,\"scripted\":false,\"indexed\":false,\"analyzed\":false,\"doc_values\":false,\"searchable\":false,\"aggregatable\":false}]"}, "id": "sortinghat_events"}], "searches": []}